README.md
setup.py
django_fixtureless.egg-info/PKG-INFO
django_fixtureless.egg-info/SOURCES.txt
django_fixtureless.egg-info/dependency_links.txt
django_fixtureless.egg-info/top_level.txt
fixtureless/__init__.py
fixtureless/constants.py
fixtureless/exceptions.py
fixtureless/factory.py
fixtureless/generator.py
fixtureless/utils.py
fixtureless/tests/__init__.py
fixtureless/tests/test_django_project/__init__.py
fixtureless/tests/test_django_project/manage.py
fixtureless/tests/test_django_project/test_django_project/__init__.py
fixtureless/tests/test_django_project/test_django_project/settings/__init__.py
fixtureless/tests/test_django_project/test_django_project/settings/base.py
fixtureless/tests/test_django_project/test_django_project/settings/mysql.py
fixtureless/tests/test_django_project/test_django_project/settings/postgres.py
fixtureless/tests/test_django_project/test_django_project/settings/sqlite.py
fixtureless/tests/test_django_project/test_django_project/test_app/__init__.py
fixtureless/tests/test_django_project/test_django_project/test_app/forms.py
fixtureless/tests/test_django_project/test_django_project/test_app/models.py
fixtureless/tests/test_django_project/test_django_project/test_app/tests/__init__.py
fixtureless/tests/test_django_project/test_django_project/test_app/tests/factory.py
fixtureless/tests/test_django_project/test_django_project/test_app/tests/generator.py
fixtureless/tests/test_django_project/test_django_project/test_app/tests/utils.py