Metadata-Version: 1.0
Name: django-fixtureless
Version: 1.6.5
Summary: Test utility to create fixtureless objects in Django.
Home-page: https://github.com/ricomoss/django-fixtureless
Author: Rico Cordova
Author-email: rico.cordova@rocksolidbox.com
License: LICENSE.txt
Keywords: unittest,django,Python 3
Platform: UNKNOWN
